datasette_hashed_urls/__init__.py
datasette_hashed_urls-0.4.dist-info/LICENSE
datasette_hashed_urls-0.4.dist-info/METADATA
datasette_hashed_urls-0.4.dist-info/WHEEL
datasette_hashed_urls-0.4.dist-info/entry_points.txt
datasette_hashed_urls-0.4.dist-info/top_level.txt
datasette_hashed_urls-0.4.dist-info/RECORD
