Metadata-Version: 2.1
Name: datasette-hashed-urls
Version: 0.4
Summary: Optimize Datasette performance behind a caching proxy
Home-page: https://github.com/simonw/datasette-hashed-urls
Author: Simon Willison
License: Apache License, Version 2.0
Project-URL: Issues, https://github.com/simonw/datasette-hashed-urls/issues
Project-URL: CI, https://github.com/simonw/datasette-hashed-urls/actions
Project-URL: Changelog, https://github.com/simonw/datasette-hashed-urls/releases
Platform: UNKNOWN
Classifier: Framework :: Datasette
Classifier: License :: OSI Approved :: Apache Software License
Requires-Python: >=3.7
License-File: LICENSE
Requires-Dist: datasette (>=0.61.1)
Provides-Extra: test
Requires-Dist: pytest ; extra == 'test'
Requires-Dist: pytest-asyncio ; extra == 'test'
Requires-Dist: sqlite-utils ; extra == 'test'
